<?xml version="1.0" encoding="utf-8" ?>
<odoo>

     <record id="customer_statements_form_view" model="ir.ui.view">
        <field name="name">customer.statements.followup</field>
        <field name="model">res.partner</field>
        <field name="type">form</field>
        <field name="inherit_id" ref="account_followup.customer_statements_form_view"/>
        <field name="arch" type="xml">
            <xpath expr="//field[@name='unreconciled_aml_ids']/tree/field[@name='amount_currency']" position="after">
                <field name="currency_name" optional="show"/>
            </xpath>
        </field>
    </record>

</odoo>